xtract/cli.py
xtract/core.py
xtract/utils.py
xtract/code/__init__.py
xtract/code/parser.py
xtract/code/processor.py
xtract/embedding/__init__.py
xtract/embedding/model.py
xtract/embedding/visualize.py
xtract/query/__init__.py
xtract/query/processor.py
xtract_nlp-0.1.2.dist-info/METADATA
xtract_nlp-0.1.2.dist-info/WHEEL
xtract_nlp-0.1.2.dist-info/entry_points.txt
xtract_nlp-0.1.2.dist-info/licenses/LICENSE
xtract_nlp-0.1.2.dist-info/RECORD
