Metadata-Version: 2.3
Name: xtract-nlp
Version: 0.1.2
Summary: A tool to process codebases, generate embeddings for code chunks, and query code snippets using natural language models like CodeBERT.
Project-URL: Homepage, https://github.com/ooojustin/xTrAct-NLP
Project-URL: Documentation, https://github.com/ooojustin/xTrAct-NLP#readme
Project-URL: Source, https://github.com/ooojustin/xTrAct-NLP
Project-URL: Tracker, https://github.com/ooojustin/xTrAct-NLP/issues
Author-email: Justin Garofolo <justin@garofolo.net>
License: MIT
License-File: LICENSE
Classifier: Development Status :: 3 - Alpha
Classifier: Intended Audience :: Developers
Classifier: Intended Audience :: Science/Research
Classifier: License :: OSI Approved :: MIT License
Classifier: Programming Language :: Python :: 3.8
Classifier: Programming Language :: Python :: 3.9
Classifier: Programming Language :: Python :: 3.10
Classifier: Programming Language :: Python :: 3.11
Classifier: Programming Language :: Python :: 3.12
Classifier: Topic :: Software Development :: Libraries :: Python Modules
Classifier: Topic :: Text Processing :: Linguistic
Classifier: Typing :: Typed
Requires-Python: >=3.8
Requires-Dist: click>=8.1.0
Requires-Dist: nltk>=3.5
Requires-Dist: scikit-learn>=1.2.0
Requires-Dist: seaborn>=0.12.0
Requires-Dist: torch>=2.0.0
Requires-Dist: transformers>=4.25.0
